{
 "charts": [],
 "content": "[{\"id\":\"594yL6PlJ_\",\"type\":\"header\",\"data\":{\"text\":\"<span class=\\\"h4\\\">Contracting</span>\",\"col\":12}},{\"id\":\"3ht8Ocu6qq\",\"type\":\"card\",\"data\":{\"card_name\":\"Contracting Documents\",\"col\":4}},{\"id\":\"NuliArDeVz\",\"type\":\"card\",\"data\":{\"card_name\":\"Selling\",\"col\":4}},{\"id\":\"USZ3z4zWFW\",\"type\":\"card\",\"data\":{\"card_name\":\"Purchases\",\"col\":4}},{\"id\":\"FrKPhBlx4B\",\"type\":\"card\",\"data\":{\"card_name\":\"Master Data\",\"col\":4}},{\"id\":\"L2o5M8uVC6\",\"type\":\"card\",\"data\":{\"card_name\":\"Installations\",\"col\":4}}]",
 "creation": "2024-08-21 18:28:01.722904",
 "custom_blocks": [],
 "docstatus": 0,
 "doctype": "Workspace",
 "for_user": "",
 "hide_custom": 0,
 "idx": 0,
 "is_hidden": 0,
 "label": "Contracting",
 "links": [
  {
   "hidden": 0,
   "is_query_report": 0,
   "label": "Selling",
   "link_count": 3,
   "link_type": "DocType",
   "onboard": 0,
   "type": "Card Break"
  },
  {
   "hidden": 0,
   "is_query_report": 0,
   "label": "Quotation",
   "link_count": 0,
   "link_to": "Quotation",
   "link_type": "DocType",
   "onboard": 0,
   "type": "Link"
  },
  {
   "hidden": 0,
   "is_query_report": 0,
   "label": "Sales Order",
   "link_count": 0,
   "link_to": "Sales Order",
   "link_type": "DocType",
   "onboard": 0,
   "type": "Link"
  },
  {
   "hidden": 0,
   "is_query_report": 0,
   "label": "Sales Invoice",
   "link_count": 0,
   "link_to": "Sales Invoice",
   "link_type": "DocType",
   "onboard": 0,
   "type": "Link"
  },
  {
   "hidden": 0,
   "is_query_report": 0,
   "label": "Contracting Documents",
   "link_count": 3,
   "link_type": "DocType",
   "onboard": 0,
   "type": "Card Break"
  },
  {
   "hidden": 0,
   "is_query_report": 0,
   "label": "Tender",
   "link_count": 0,
   "link_to": "Tender",
   "link_type": "DocType",
   "onboard": 0,
   "type": "Link"
  },
  {
   "hidden": 0,
   "is_query_report": 0,
   "label": "Contract Document",
   "link_count": 0,
   "link_to": "Contract Document",
   "link_type": "DocType",
   "onboard": 0,
   "type": "Link"
  },
  {
   "hidden": 0,
   "is_query_report": 0,
   "label": "Costing Note",
   "link_count": 0,
   "link_to": "Costing Note",
   "link_type": "DocType",
   "onboard": 0,
   "type": "Link"
  },
  {
   "hidden": 0,
   "is_query_report": 0,
   "label": "Master Data",
   "link_count": 7,
   "link_type": "DocType",
   "onboard": 0,
   "type": "Card Break"
  },
  {
   "hidden": 0,
   "is_query_report": 0,
   "label": "Project",
   "link_count": 0,
   "link_to": "Project",
   "link_type": "DocType",
   "onboard": 0,
   "type": "Link"
  },
  {
   "hidden": 0,
   "is_query_report": 0,
   "label": "Customer",
   "link_count": 0,
   "link_to": "Customer",
   "link_type": "DocType",
   "onboard": 0,
   "type": "Link"
  },
  {
   "hidden": 0,
   "is_query_report": 0,
   "label": "Suplier",
   "link_count": 0,
   "link_to": "Supplier",
   "link_type": "DocType",
   "onboard": 0,
   "type": "Link"
  },
  {
   "hidden": 0,
   "is_query_report": 0,
   "label": "Engineering consulting office",
   "link_count": 0,
   "link_to": "Engineering consulting office",
   "link_type": "DocType",
   "onboard": 0,
   "type": "Link"
  },
  {
   "hidden": 0,
   "is_query_report": 0,
   "label": "Project Processing Status",
   "link_count": 0,
   "link_to": "Project Processing Status",
   "link_type": "DocType",
   "onboard": 0,
   "type": "Link"
  },
  {
   "hidden": 0,
   "is_query_report": 0,
   "label": "Project Classification",
   "link_count": 0,
   "link_to": "Project Classification",
   "link_type": "DocType",
   "onboard": 0,
   "type": "Link"
  },
  {
   "hidden": 0,
   "is_query_report": 0,
   "label": "Project Engineer",
   "link_count": 0,
   "link_to": "Project Engineer",
   "link_type": "DocType",
   "onboard": 0,
   "type": "Link"
  },
  {
   "hidden": 0,
   "is_query_report": 0,
   "label": "Purchases",
   "link_count": 3,
   "link_type": "DocType",
   "onboard": 0,
   "type": "Card Break"
  },
  {
   "hidden": 0,
   "is_query_report": 0,
   "label": "Purchase Order",
   "link_count": 0,
   "link_to": "Purchase Order",
   "link_type": "DocType",
   "onboard": 0,
   "type": "Link"
  },
  {
   "hidden": 0,
   "is_query_report": 0,
   "label": "Purchase Invoice",
   "link_count": 0,
   "link_to": "Purchase Invoice",
   "link_type": "DocType",
   "onboard": 0,
   "type": "Link"
  },
  {
   "hidden": 0,
   "is_query_report": 0,
   "label": "Material Request",
   "link_count": 0,
   "link_to": "Material Request",
   "link_type": "DocType",
   "onboard": 0,
   "type": "Link"
  },
  {
   "hidden": 0,
   "is_query_report": 0,
   "label": "Installations",
   "link_count": 1,
   "link_type": "DocType",
   "onboard": 0,
   "type": "Card Break"
  },
  {
   "hidden": 0,
   "is_query_report": 0,
   "label": "Installation Note",
   "link_count": 0,
   "link_to": "Installation Note",
   "link_type": "DocType",
   "onboard": 0,
   "type": "Link"
  }
 ],
 "modified": "2025-01-21 07:07:29.705783",
 "modified_by": "Administrator",
 "module": "Contracting",
 "name": "Contracting",
 "number_cards": [],
 "owner": "Administrator",
 "parent_page": "",
 "public": 1,
 "quick_lists": [],
 "roles": [],
 "sequence_id": 23.0,
 "shortcuts": [],
 "title": "Contracting"
}